state_machine/openlane/state_machine.v
module state_machine(
	input clk,
	input rst_z,
	input start,
	input single_ended,
	input en_offset_cal,
	input comp_p, comp_n,
	input vin_p_sw_on, vin_n_sw_on,
	input [3:0] debug_mux,
	input en_vcm_sw_o_i,
	input [10:0] vcm_o_i,
	
	output [5:0] data,
	output clk_data,
	output sample_o,
	output reg [10:0] vcm_o,
	output reg [10:0] vref_z_p_o,
	output reg [10:0] vref_z_n_o,
	output reg [10:0] vss_p_o,
	output reg [10:0] vss_n_o,
	output reg vcm_dummy_o,
	output reg en_vcm_sw_o,
	output reg en_comp,
	output reg offset_cal_cycle,
	output reg en_offset_cal_o,
	output reg debug_out);

reg [1:0] state;
reg [11:0] result;
parameter idle = 0, sample = 1, convert = 2;



always @(posedge clk or negedge rst_z)
begin
	if (!rst_z)
		state <= idle;
	else
		case (state)
			idle:
				if (start)
					state <= sample;
				else
					state <= idle;
			sample:
				if (counter_sample)
					state <= convert;
				else
					state <= sample;
			convert:
				if ((counter == 'b111111111111 && ~single_ended_reg) || (counter == 'b111111111110 && single_ended_reg))
					state <= idle;
				else
					state <= convert;
			default:
				state <= idle;
		endcase
end



reg counter_sample;
always @ (posedge clk or negedge rst_z)
begin
	if (!rst_z)
		counter_sample <= 0;
	else if (state != sample)
		counter_sample <= 0;
	else
		counter_sample <= ~ counter_sample;
end

reg single_ended_reg;
always @ (posedge clk or negedge rst_z)
begin
	if (!rst_z)
		single_ended_reg <= 0;
	else if (state == idle)
		single_ended_reg <= single_ended;
end

reg [11:0] counter;

always @ (posedge clk or negedge rst_z)
begin
	if (!rst_z)
		counter <= 'b000000000000;
	else if (state == idle || state  == sample)
		counter <= 'b000000000000;
	else if (state == convert) begin
		counter <= counter >> 1;
		counter[11] <= 1;
	end
end

integer i;

wire [11:0] en_dac_out;
assign en_dac_out = (~ counter) & ('b100000000000 + (counter >> 1));


always @(posedge clk or negedge rst_z)
begin
	if (!rst_z) begin
		result <= 'd0;
	end else if (clk) begin
		if (state == sample)
			result <= 'd0;
		else if (state == convert) begin
			if (single_ended_reg) begin
				for (i = 0; i < 11; i = i + 1) begin
					result[i] <= en_dac_out[i+1] ? comp_p : result[i];
				end
				result[11] <= 0;
			end else begin
				for (i = 0; i < 12; i = i + 1) begin
					result[i] <= en_dac_out[i] ? comp_p : result[i];
				end
			end

		end
	end
end

reg allow_vcm_sw;
reg [10:0] allow_vref_sw;

assign sample_o = ((state == sample) | en_vcm_sw_o_i) & ~counter[11] & (state != idle);

always @(*)
begin
	en_offset_cal_o <= rst_z & en_offset_cal;
	allow_vcm_sw <= ~(vin_p_sw_on | vin_n_sw_on);
	vcm_dummy_o <= (state == convert) & allow_vcm_sw;
	if (single_ended_reg) begin
		en_comp <= ~clk & (state == convert) & ~(~ en_offset_cal & counter[1]);
		offset_cal_cycle <= counter[1] & en_offset_cal;
		vcm_o <= 'd0;
		vref_z_p_o <= result[10:0] | (~ allow_vref_sw);
		vref_z_n_o <= 'b11111111111;
		vss_p_o <= (result[10:0] | (~ allow_vref_sw)) & {11 {(state == convert) & allow_vcm_sw}};
		vss_n_o <= {11 {(state == convert) & allow_vcm_sw}};
		en_vcm_sw_o <= (counter[1] & (state == convert)) | (state == sample);
		allow_vref_sw <= {11 {(state == convert) & allow_vcm_sw}} & {1'b1,counter[11:2]};
	end else begin
		en_comp <= ~clk & (state == convert) & ~(~ en_offset_cal & counter[0]);
		offset_cal_cycle <= counter[0] & en_offset_cal;
		vcm_o <= ~(counter[11:1] | {11 {~((state == convert) & allow_vcm_sw)}});
		vref_z_p_o <= result[11:1] | (~ allow_vref_sw);
		vref_z_n_o <= (~result[11:1]) | (~ allow_vref_sw);
		vss_p_o <= result[11:1] & allow_vref_sw;
		vss_n_o <= (~result[11:1]) & allow_vref_sw;
		en_vcm_sw_o <= (counter[0] & (state == convert)) | (state == sample);
		allow_vref_sw <= (~ vcm_o_i) & counter[11:1];
	end
end


always @(*)
begin
	case (debug_mux)
		'd0: debug_out = (state == idle);
		'd1: debug_out = (state == sample);
		'd2: debug_out = (state == convert);
		'd3: debug_out = en_comp;
		'd4: debug_out = comp_p | comp_n;
		'd5: debug_out = comp_p;
		'd6: debug_out = comp_n;
		'd7: debug_out = counter[11];
		'd8: debug_out = counter[10];
		'd9: debug_out = counter[9];
		'd10: debug_out = counter[8];
		'd11: debug_out = counter[7];
		'd12: debug_out = counter[6];
		'd13: debug_out = counter[4];
		'd14: debug_out = counter[2];
		'd15: debug_out = counter[0];
	endcase
end

assign clk_data = counter[5] & (state == convert);
assign data = counter[4] ? ~result[5:0] : {~(result[11] | single_ended_reg),~result[10:6]};

endmodule

schematic/subcells/state_machine/openlane/state_machine_sim.v
module state_machine_sim;

	reg clk;
	reg rst_z;
	reg start;
	reg single_ended;
	reg en_offset_cal;
	reg comp_p;
	reg comp_n;
	reg vin_p_sw_on;
	reg vin_n_sw_on;
	reg [3:0] debug_mux;
	
	wire [5:0] data;
	wire clk_data;
	wire sample_o;
	wire [10:0] vcm;
	wire [10:0] vref_z_p;
	wire [10:0] vref_z_n;
	wire [10:0] vss_p;
	wire [10:0] vss_n;
	wire vcm_dummy; 
	wire en_vcm_sw;
	wire en_comp;
	wire offset_cal_cycle;
	wire en_offset_cal_o;
	wire debug_out;
	
	wire en_vcm_sw_i;
	wire [10:0] vcm_i;
	
	state_machine dut(
		.clk(clk),
		.rst_z(rst_z),
		.start(start),
		.single_ended(single_ended),
		.en_offset_cal(en_offset_cal),
		.comp_p(comp_p),
		.comp_n(comp_n),
		.vin_p_sw_on(vin_p_sw_on),
		.vin_n_sw_on(vin_n_sw_on),
		.debug_mux(debug_mux),
		.en_vcm_sw_o_i(en_vcm_sw_i),
		.vcm_o_i(vcm_i),
		.data(data),
		.clk_data(clk_data),
		.sample_o(sample_o),
		.vcm_o(vcm),
		.vref_z_p_o(vref_z_p),
		.vref_z_n_o(vref_z_n),
		.vss_p_o(vss_p),
		.vss_n_o(vss_n),
		.vcm_dummy_o(vcm_dummy),
		.en_vcm_sw_o(en_vcm_sw),
		.en_comp(en_comp),
		.offset_cal_cycle(offset_cal_cycle),
		.en_offset_cal_o(en_offset_cal_o),
		.debug_out(debug_out));

	assign en_vcm_sw_i = en_vcm_sw;
	assign vcm_i = vcm;

	initial begin
		$dumpfile("state_machine.vcd");
		$dumpvars(0,state_machine_sim);
		clk = 0;
		rst_z = 0;
		start = 0;
		single_ended = 0;
		en_offset_cal = 1;
		comp_p = 0;
		comp_n = 0;
		vin_p_sw_on = 0;
		vin_n_sw_on = 0;
		debug_mux = 'd0;
		
		#100
		rst_z = 1;
		#100
		start = 1;
		#100
		start = 0;
		#1000
		single_ended = 1;
		#100
		start = 1;
		#100
		start = 0;
		#500
		$finish();
	
	
	end



	always #10 clk = ~clk;


endmodule

state_machine/openlane/state_machine.vcd
$date
	Sun Apr 14 19:18:25 2024
$end
$version
	Icarus Verilog
$end
$timescale
	1s
$end
$scope module state_machine_sim $end
$var wire 1 ! en_vcm_sw_i $end
$var wire 11 " vcm_i [10:0] $end
$var wire 11 # vss_p [10:0] $end
$var wire 11 $ vss_n [10:0] $end
$var wire 11 % vref_z_p [10:0] $end
$var wire 11 & vref_z_n [10:0] $end
$var wire 1 ' vcm_dummy $end
$var wire 11 ( vcm [10:0] $end
$var wire 1 ) sample_o $end
$var wire 1 * offset_cal_cycle $end
$var wire 1 + en_vcm_sw $end
$var wire 1 , en_offset_cal_o $end
$var wire 1 - en_comp $end
$var wire 1 . debug_out $end
$var wire 6 / data [5:0] $end
$var wire 1 0 clk_data $end
$var reg 1 1 clk $end
$var reg 1 2 comp_n $end
$var reg 1 3 comp_p $end
$var reg 4 4 debug_mux [3:0] $end
$var reg 1 5 en_offset_cal $end
$var reg 1 6 rst_z $end
$var reg 1 7 single_ended $end
$var reg 1 8 start $end
$var reg 1 9 vin_n_sw_on $end
$var reg 1 : vin_p_sw_on $end
$scope module dut $end
$var wire 1 1 clk $end
$var wire 1 0 clk_data $end
$var wire 1 2 comp_n $end
$var wire 1 3 comp_p $end
$var wire 4 ; debug_mux [3:0] $end
$var wire 1 5 en_offset_cal $end
$var wire 1 ! en_vcm_sw_o_i $end
$var wire 1 6 rst_z $end
$var wire 1 ) sample_o $end
$var wire 1 7 single_ended $end
$var wire 1 8 start $end
$var wire 11 < vcm_o_i [10:0] $end
$var wire 1 9 vin_n_sw_on $end
$var wire 1 : vin_p_sw_on $end
$var wire 12 = en_dac_out [11:0] $end
$var wire 6 > data [5:0] $end
$var parameter 32 ? convert $end
$var parameter 32 @ idle $end
$var parameter 32 A sample $end
$var reg 1 B allow_vcm_sw $end
$var reg 11 C allow_vref_sw [10:0] $end
$var reg 12 D counter [11:0] $end
$var reg 1 E counter_sample $end
$var reg 1 . debug_out $end
$var reg 1 - en_comp $end
$var reg 1 , en_offset_cal_o $end
$var reg 1 + en_vcm_sw_o $end
$var reg 1 * offset_cal_cycle $end
$var reg 12 F result [11:0] $end
$var reg 1 G single_ended_reg $end
$var reg 2 H state [1:0] $end
$var reg 1 ' vcm_dummy_o $end
$var reg 11 I vcm_o [10:0] $end
$var reg 11 J vref_z_n_o [10:0] $end
$var reg 11 K vref_z_p_o [10:0] $end
$var reg 11 L vss_n_o [10:0] $end
$var reg 11 M vss_p_o [10:0] $end
$var integer 32 N i [31:0] $end
$upscope $end
$upscope $end
$enddefinitions $end
$comment Show the parameter values. $end
$dumpall
b1 A
b0 @
b10 ?
$end
#0
$dumpvars
bx N
b0 M
b0 L
b11111111111 K
b11111111111 J
b0 I
b0 H
0G
b0 F
0E
b0 D
b0 C
1B
b111111 >
b100000000000 =
b0 <
b0 ;
0:
09
08
07
06
15
b0 4
03
02
01
00
b111111 /
1.
0-
0,
0+
0*
0)
b0 (
0'
b11111111111 &
b11111111111 %
b0 $
b0 #
b0 "
0!
$end
#10
11
#20
01
#30
11
#40
01
#50
11
#60
01
#70
11
#80
01
#90
11
#100
1,
01
16
#110
11
#120
01
#130
11
#140
01
#150
11
#160
01
#170
11
#180
01
#190
11
#200
01
18
#210
1!
1+
1)
0.
b1 H
11
#220
01
#230
1E
11
#240
01
#250
0)
0!
0+
b11111111111 "
b11111111111 <
b11111111111 (
b11111111111 I
1'
0E
b10 H
11
#260
1-
01
#270
b10000000000 $
b10000000000 L
b1111111111 %
b1111111111 K
b10000000000 C
b1111111111 "
b1111111111 <
b1111111111 (
b1111111111 I
b10000000000 =
0-
b100000000000 D
b1100 N
11
#280
1-
01
#290
b11000000000 $
b11000000000 L
b111111111 %
b111111111 K
b11000000000 C
b111111111 "
b111111111 <
b111111111 (
b111111111 I
b1000000000 =
0-
b110000000000 D
b1100 N
11
#300
1-
01
08
#310
b11100000000 $
b11100000000 L
b11111111 %
b11111111 K
b11100000000 C
b11111111 "
b11111111 <
b11111111 (
b11111111 I
b100000000 =
0-
b111000000000 D
b1100 N
11
#320
1-
01
#330
b11110000000 $
b11110000000 L
b1111111 %
b1111111 K
b11110000000 C
b1111111 "
b1111111 <
b1111111 (
b1111111 I
b10000000 =
0-
b111100000000 D
b1100 N
11
#340
1-
01
#350
b11111000000 $
b11111000000 L
b111111 %
b111111 K
b11111000000 C
b111111 "
b111111 <
b111111 (
b111111 I
b1000000 =
0-
b111110000000 D
b1100 N
11
#360
1-
01
#370
b11111100000 $
b11111100000 L
b11111 %
b11111 K
b11111100000 C
b11111 "
b11111 <
b11111 (
b11111 I
b100000 =
0-
b111111000000 D
b1100 N
11
#380
1-
01
#390
b11111110000 $
b11111110000 L
b1111 %
b1111 K
b11111110000 C
b1111 "
b1111 <
b1111 (
b1111 I
b10000 =
10
0-
b111111100000 D
b1100 N
11
#400
1-
01
#410
b11111111000 $
b11111111000 L
b111 %
b111 K
b11111111000 C
b111 "
b111 <
b111 (
b111 I
b1000 =
0-
b111111110000 D
b1100 N
11
#420
1-
01
#430
b11111111100 $
b11111111100 L
b11 %
b11 K
b11111111100 C
b11 "
b11 <
b11 (
b11 I
b100 =
0-
b111111111000 D
b1100 N
11
#440
1-
01
#450
b11111111110 $
b11111111110 L
b1 %
b1 K
b11111111110 C
b1 "
b1 <
b1 (
b1 I
b10 =
0-
b111111111100 D
b1100 N
11
#460
1-
01
#470
b11111111111 $
b11111111111 L
b0 %
b0 K
b11111111111 C
b0 "
b0 <
b0 (
b0 I
b1 =
0-
b111111111110 D
b1100 N
11
#480
1-
01
#490
1!
1+
1*
b0 =
0-
b111111111111 D
b1100 N
11
#500
1-
01
#510
0!
0+
0'
00
1.
0-
b0 H
b111111111111 D
b1100 N
11
#520
01
#530
b0 $
b0 L
b11111111111 %
b11111111111 K
b0 C
0*
b100000000000 =
b0 D
11
